[
  {
    "id": 1,
    "title": "title",
    "summary": "Two imprisoned try to scape",
    "tags": ["drama", "prison", "freedom"],
    "text": "lorem ipsum dolor sit amet"
  },
  {
    "id": 2,
    "title": "title2",
    "summary": "summary2",
    "tags": ["drama", "prison", "freedom"],
    "text": "lorem ipsum dolor sit amet2"
  },
  {
    "id": 3,
    "title": "title3",
    "summary": "summary3",
    "tags": ["drama", "prison", "freedom"],
    "text": "lorem ipsum dolor sit amet3"
  },
  {
    "id": 4,
    "title": "title4",
    "summary": "Two imprisoned try to scape4",
    "tags": ["drama", "prison", "freedom"],
    "text": "lorem ipsum dolor sit amet4"
  },
  {
    "id": 5,
    "title": "title5",
    "summary": "Two imprisoned try to scape5",
    "tags": ["drama", "prison", "freedom"],
    "text": "lorem ipsum dolor sit amet5"
  },
  {
    "id": 6,
    "title": "a",
    "summary": "Two imprisoned try to scape5",
    "tags": ["drama", "prison", "freedom"],
    "text": "lorem ipsum dolor sit amet5"
  }
]
